{"url": "Ori", "categories": ["Category:Legends articles", "Category:Males", "Category:Officers", "Category:Otolla Gungans"], "nodes": [{"tag": "h1", "text": "Ori"}, {"tag": "p", "text": "Ori was a Gungan male warrior who lived on Naboo's moon of Rori during the Galactic Civil War. He was a member of the Rorgungans, a group of extremist Gungans who violently opposed Boss Rugor Nass's support of Naboo's human population during the Invasion of Naboo and rejected any alliance between humans and Gungans. By the time of the Battle of Yavin, Lieutenant Ori served under Captain Hassk, the Rorgungan commander, in the Gungan Swamp Town, along with fellow Lieutenant Heb Nee."}, {"tag": "h2", "text": "Behind the scenes"}, {"tag": "p", "text": "Lieutenant Ori appeared as a non-player character in the 2003 video game Star Wars Galaxies, a massively multiplayer online-role playing game developed by Sony Online Entertainment and published by LucasArts, prior to its closure on December 15, 2011. Ori was added to the game with the \"Publish 1\" update, released on August 3, 2003."}, {"tag": "h2", "text": "Appearances"}, {"tag": "h2", "text": "Sources"}, {"tag": "h2", "text": "Notes and references"}, {"tag": "h2", "text": "External links"}]}