{"url": "Phosphor_bug", "categories": ["Category:Legends articles", "Category:Creature stubs", "Category:Bioluminescent creatures", "Category:Creatures of Belsavis", "Category:Creatures of unspecified diet", "Category:Flying creatures", "Category:Insects", "Category:Species of undefined sentience"], "nodes": [{"tag": "h1", "text": "Phosphor bug"}, {"tag": "p", "text": "Phosphor bugs, also known as firebugs, were flying insects that flashed light. They were native to Belsavis."}, {"tag": "h2", "text": "Appearances"}]}