{"url": "Pik", "categories": ["Category:Canon articles", "Category:Character stubs", "Category:Death troopers", "Category:Guards", "Category:Humans", "Category:Males", "Category:Pilots"], "nodes": [{"tag": "h1", "text": "Pik"}, {"tag": "p", "text": "Pik was a human male death trooper who served Grand Admiral Thrawn. Pik and Waffle, another death trooper, were assigned by Grand Admiral Thrawn to accompany Assistant Director Brierly Ronan and Lieutenant Eli Vanto of the Chiss Expansionary Defense Fleet to Tiquwe on the planet Aloxor."}, {"tag": "h2", "text": "Appearances"}, {"tag": "h2", "text": "Notes and references"}]}