{"url": "Quatermass", "categories": ["Category:Legends articles", "Category:Engineers", "Category:Humans", "Category:Imperial Corrections Service personnel", "Category:Males"], "nodes": [{"tag": "h1", "text": "Quatermass"}, {"tag": "p", "text": "Quatermass was a Human male who served the Galactic Empire as an engineer during the time of the Galactic Civil War."}, {"tag": "h2", "text": "Biography"}, {"tag": "p", "text": "Quatermass served in the Imperial Corrections Service aboard the Imperial prison barge Purge and was aboard it in 1 BBY when the barge broke down while en route to the detainment moon Gradient Seven. Quatermass was selected to be part of a boarding party that was to travel from the Purge to the nearby abandoned Star Destroyer Vector, to search for spare parts to try and repair the barge with. The team was led by Jareth Sartoris and it made it's way onto the Star Destroyer through a docking shaft. They then split into two, which Quatermass going off with a group under the command of the Imperial Corrections Officer Armitage, along with his fellow engineer Phibes and a pair of stormtroopers. However, Quatermass and the rest of the team contracted a virus that had infected the Star Destroyer, and died."}, {"tag": "h2", "text": "Appearances"}]}