{"url": "R300-H_hyperdrive_motivator/Legends", "categories": ["Category:Legends articles", "Category:Hyperdrive motivators", "Category:Koensayr Manufacturing products"], "nodes": [{"tag": "h1", "text": "R300-H hyperdrive motivator"}, {"tag": "p", "text": "The R300-H hyperdrive motivator was a hyperdrive motivator produced by Koensayr Manufacturing and used in the BTL Y-wing starfighter and some T-65B X-wing starfighters. It yielded a class one performance on standard hyperspace routes."}, {"tag": "h2", "text": "Sources"}]}