{"url": "Ranath", "categories": ["Category:Legends articles", "Category:Character stubs", "Category:Humans", "Category:Males", "Category:Sith Lords of the reconstituted Sith Empire"], "nodes": [{"tag": "h1", "text": "Ranath"}, {"tag": "p", "text": "Ranath was a Human male Sith Lord of the reconstituted Sith Empire during the Galactic War, during which he was stationed on Hoth."}, {"tag": "h2", "text": "Appearances"}, {"tag": "h2", "text": "Sources"}, {"tag": "h2", "text": "Notes and references"}]}