{"url": "Ringneldia_II", "categories": ["Category:Legends articles", "Category:Centrality planets", "Category:Ringneldia system"], "nodes": [{"tag": "h1", "text": "Ringneldia II"}, {"tag": "p", "text": "Ringneldia II, also known simply as Ringneldia, was an industrial planet located in the Centrality, a sector of the Outer Rim Territories."}, {"tag": "h2", "text": "Description"}, {"tag": "p", "text": "Ringneldia II was the Centrality's manufacturing center, using a unique a local measurement system based around the diameter of the Ringneldian bean. This made Ringneldia's products totally incompatible with products using the galactic standard of measurements."}, {"tag": "h2", "text": "Behind the scenes"}, {"tag": "p", "text": "Ringneldia was misspelled Rigneldia in Star Wars Gamer 5. The Essential Atlas confirmed the correct spelling."}, {"tag": "h2", "text": "Sources"}, {"tag": "h2", "text": "Notes and references"}]}