{"url": "Rivoche_Ranges", "categories": ["Category:Canon articles", "Category:General location stubs", "Category:Eriadu locations", "Category:Mountain ranges"], "nodes": [{"tag": "h1", "text": "Rivoche Ranges"}, {"tag": "p", "text": "The Rivoche Ranges were a chain of mountains on Eriadu, a planet in the Outer Rim Territories."}, {"tag": "h2", "text": "Behind the scenes"}, {"tag": "p", "text": "The Rivoche Ranges were first mentioned in the 2017 young adult novel Leia, Princess of Alderaan, by author Claudia Gray. The Rivoche Ranges share their name with the Star Wars Legends character Rivoche Tarkin, who was from Eriadu."}, {"tag": "h2", "text": "Appearances"}, {"tag": "h2", "text": "Notes and references"}]}