{"url": "Bafwizzy", "categories": ["Category:Legends articles", "Category:Jospro sector", "Category:Outer Rim Territories moons"], "nodes": [{"tag": "h1", "text": "Bafwizzy"}, {"tag": "p", "text": "Bafwizzy was a moon that orbited the Outer Rim planet Chad. It was the largest and greenest of Chad's nine moons and was visible in the sky at the time of the Chadran disaster, a groundquake and tsunami that killed many of Chad's native Chadra-Fan."}, {"tag": "h2", "text": "Sources"}, {"tag": "h2", "text": "Notes and references"}]}