{"url": "Balti", "categories": ["Category:Legends articles", "Category:Races and species stubs", "Category:Balti", "Category:Mammalian sentient species"], "nodes": [{"tag": "h1", "text": "Balti"}, {"tag": "p", "text": "The Balti were a species of furry bipeds with prominent tusks. The smuggler Bingo Mehndra was a Balti."}, {"tag": "p", "text": "Rather than a birthday or a hatching day, Balti celebrated their \"Spawning Day.\""}, {"tag": "h2", "text": "Behind the scenes"}, {"tag": "p", "text": "Balti strongly resembles the Khormai species."}, {"tag": "h2", "text": "Appearances"}]}