{"url": "Solenbaran_Merchant_Route", "categories": ["Category:Legends articles", "Category:Corporate Sector hyperlanes", "Category:Outer Rim Territories hyperlanes"], "nodes": [{"tag": "h1", "text": "Solenbaran Merchant Route"}, {"tag": "p", "text": "The Solenbaran Merchant Route was a remote hyperspace trade route that connected the distant world of Saclas with more profitable and populous worlds such as Etti IV and Bonadan."}, {"tag": "h2", "text": "Sources"}, {"tag": "h2", "text": "Notes and references"}]}