{"url": "Barium_liquid", "categories": ["Category:Legends articles", "Category:Food and beverage stubs", "Category:Food at Dex's Diner", "Category:Sauces"], "nodes": [{"tag": "h1", "text": "Barium liquid"}, {"tag": "p", "text": "Barium liquid was a sauce or beverage of some kind served with various meals. Roast smapp was served with hot barium liquid as a Pantoran plate special on Zhelldays in Dex's Diner on the planet Coruscant for 8.5 credits."}, {"tag": "h2", "text": "Behind the scenes"}, {"tag": "p", "text": "Barium liquid may simply be the liquid form of the real world element barium."}, {"tag": "h2", "text": "Appearances"}, {"tag": "h2", "text": "Sources"}]}