{"url": "Spice_Mines_of_Kemix", "categories": ["Category:Legends articles", "Category:Mining areas"], "nodes": [{"tag": "h1", "text": "Spice Mines of Kemix"}, {"tag": "p", "text": "The Spice Mines of Kemix was a spice-mining operation that was established on the planet Kemix by the Hutt crime lord Riboga during the Clone Wars, after he discovered naturally-occurring deposits of glitterstim on the world. However, the mine was subsequently destroyed by the Heroes of Cularin\u2014a band of freelance agents from the Cularin system\u2014which crippled Riboga's criminal empire."}, {"tag": "h2", "text": "Appearances"}]}