{"url": "Squall_(shuttle)", "categories": ["Category:Legends articles", "Category:Galactic Republic starships", "Category:Shuttles"], "nodes": [{"tag": "h1", "text": "Squall (shuttle)"}, {"tag": "p", "text": "The Squall was a combat shuttle that was assigned to the Republic cruiser Maelstrom during the Clone Wars. In 19 BBY, the ARC trooper Mar'ek received a transmission from the Supreme Chancellor Palpatine while on the bridge of the Squall, ordering the trooper to execute the contingency directive Order 66."}, {"tag": "h2", "text": "Appearances"}]}