{"url": "Thorilide_shock_absorber", "categories": ["Category:Canon articles", "Category:Weapon components"], "nodes": [{"tag": "h1", "text": "Thorilide shock absorber"}, {"tag": "p", "text": "Thorilide shock absorbers were components used in the creation of point-defense turbolaser batteries. Along with other such components, they were stolen by Grand Admiral Balanhai Savit from supplies directed towards Project Stardust."}, {"tag": "h2", "text": "Appearances"}, {"tag": "h2", "text": "Notes and references"}]}