{"url": "Tir_training_school", "categories": ["Category:Legends articles", "Category:Schools"], "nodes": [{"tag": "h1", "text": "Tir training school"}, {"tag": "p", "text": "The Tir training school was an Imperial Navy institution for training TIE pilots. The school itself was based on the Imperial-class Star Destroyer Inflexible. Flight Captain T. Alvak was one of its graduates."}, {"tag": "h2", "text": "Behind the scenes"}, {"tag": "p", "text": "In the original entry, Alvak was noted as attending the \"TIE training school\" aboard the Star Destroyer Inflexible. In the 1994 entry, this was changed to \"Tir training school\". This article assumes that the later information is correct."}, {"tag": "h2", "text": "Sources"}]}