{"url": "Uneti_blossom", "categories": ["Category:Canon articles", "Category:Plant stubs", "Category:Flowers"], "nodes": [{"tag": "h1", "text": "Uneti blossom"}, {"tag": "p", "text": "Uneti blossom was a pink, pleasant smelling flower which bloomed from uneti trees. During the High Republic Era, Jedi Master Wishan created incense using the petals from the blossoms which Stellan Gios found invaluable to use during Meditation. During the Republic Fair on Valo, several uneti blossoms were on display suspended in a repulsor field."}, {"tag": "h2", "text": "Appearances"}, {"tag": "h2", "text": "Notes and references"}]}