{"url": "Unidentified_nurse_(Executor)", "categories": ["Category:Legends articles", "Category:Articles with conjectural titles", "Category:Character stubs", "Category:Death Squadron personnel", "Category:Individuals of unspecified gender", "Category:Individuals of unspecified species", "Category:Nurses", "Category:Unidentified Galactic Empire personnel"], "nodes": [{"tag": "h1", "text": "Unidentified nurse  (Executor)"}, {"tag": "p", "text": "A nurse was on duty in the infirmary ward of the Super Star Destroyer Executor in 3 ABY, during the vessel's murder investigation into the death of Lieutenant Commander Tanith Sorn. This nurse tended to the critically wounded Lieutenant Ein Truminn."}, {"tag": "h2", "text": "Appearances"}]}