{"url": "University_of_Yabol_Opa/Legends", "categories": ["Category:Legends articles", "Category:Capital cities", "Category:Universities"], "nodes": [{"tag": "h1", "text": "University of Yabol Opa"}, {"tag": "p", "text": "The University of Yabol Opa was an institution of higher education that covered the entire planet of Yabol Opa. Solokin Sakellar was its Grand Warden and absolute ruler at the outbreak of the Clone Wars; one of his perks was a Lodge on Coruscant."}, {"tag": "h2", "text": "Sources"}]}