{"url": "Bovit_Leebo", "categories": ["Category:Legends articles", "Category:Holographers", "Category:Individuals of unspecified gender", "Category:Rodians"], "nodes": [{"tag": "h1", "text": "Bovit Leebo"}, {"tag": "p", "text": "Bovit Leebo was a famed Rodian holographer. Leebo captured the famous image of Ka'Pa the Hutt which would later be featured in Riccix's Revised Basic Holodictionary. The image fell into public domain after the Rodian holographer was killed by Ka'Pa's agent."}, {"tag": "h2", "text": "Sources"}]}