{"url": "Buzzee%27s", "categories": ["Category:Legends articles", "Category:Wookieepedia Comprehensive articles", "Category:Dining establishments", "Category:Mos Eisley locations"], "nodes": [{"tag": "h1", "text": "Buzzee's"}, {"tag": "p", "text": "Buzzee's was the name of a restaurant that was located in Mos Eisley spaceport on the planet Tatooine during the reign of the New Republic. The Human scholar Ebenn Q3 Baobab claimed that the food at Buzzee's, all of which was insect-based, was unique and reasonably priced in the Galactic Phrase Book & Travel Guide he authored in 6 ABY. Baobab also declared in the book that the larvae served at the restaurant were the best available in the Outer Rim Territories and included the establishment in a list of what he thought were the finest eateries in Mos Eisley."}, {"tag": "h2", "text": "Behind the scenes"}, {"tag": "p", "text": "Buzzee's was first mentioned in the Galactic Phrase Book & Travel Guide, a book written by Ben Burtt that was released in 2001."}, {"tag": "h2", "text": "Sources"}, {"tag": "h2", "text": "Notes and references"}]}