{"url": "Byss_cheese", "categories": ["Category:Legends articles", "Category:Food and beverage stubs", "Category:Cheeses"], "nodes": [{"tag": "h1", "text": "Byss cheese"}, {"tag": "p", "text": "Created by the Abyssin species, Byss cheese was a cheese noted for its large holes.\nThe fact its hole were so noticeable meant that similarly cratered planets and moons were referred to as Byss cheese. For example, Yavin 13; the thirteenth moon of Yavin Prime"}, {"tag": "h2", "text": "Appearances"}, {"tag": "h2", "text": "Sources"}]}