{"url": "Carbonite_Guild", "categories": ["Category:Legends articles", "Category:Conglomerates", "Category:Mining companies"], "nodes": [{"tag": "h1", "text": "Carbonite Guild"}, {"tag": "p", "text": "The Carbonite Guild was a powerful carbonite-mining conglomerate that rose to prominence on Empress Teta between the Great Hyperspace and Great Sith Wars. By the time of the latter, it was associated with the Mining Guild and shared rule of the Empress Teta system with the Tetan royalty. It was lead by Chairman Bearus."}, {"tag": "p", "text": "After Satal and Aleema Keto's Krath rose to power, the Guild's prominence was shattered."}, {"tag": "h2", "text": "Behind the scenes"}, {"tag": "p", "text": "Its relation to Carbonite Miners' Union is unknown."}, {"tag": "h2", "text": "Appearances"}, {"tag": "h2", "text": "Sources"}]}