{"url": "Cavitation_hyperdrive", "categories": ["Category:Legends articles", "Category:Hyperdrive units"], "nodes": [{"tag": "h1", "text": "Cavitation hyperdrive"}, {"tag": "p", "text": "The cavitation hyperdrive was a type of hyperdrive."}, {"tag": "h2", "text": "History"}, {"tag": "p", "text": "The Mon Calamari mathematician Q-Viza was credited with its invention and it was used by the Calamari to allow them to establish colonies on Ruisto, Mantan and Hinakuu between 4400 BBY and 4200 BBY. However, it was exponentially slower than the standard Corellian hyperdrive, which limited the territorial expansion of the Mon Calamari."}, {"tag": "h2", "text": "Sources"}]}