{"url": "Create_Force_Wraith", "categories": ["Category:Legends articles", "Category:Articles from unlicensed sources", "Category:Dark side powers"], "nodes": [{"tag": "h1", "text": "Create Force Wraith"}, {"tag": "p", "text": "Create Force Wraith was the Force power which allowed Force-users to create Force Wraiths. Because of the nature of this power, creating a being of dark side energies, the user was seduced more and more by the dark side each time they used it."}, {"tag": "h2", "text": "Sources"}]}