{"url": "Dartibek_system", "categories": ["Category:Legends articles", "Category:Atrivis sector star systems", "Category:Yuuzhan Vong empire star systems"], "nodes": [{"tag": "h1", "text": "Dartibek system"}, {"tag": "p", "text": "The Dartibek system (sometimes known as the Moltok system) was located in the Atrivis sector of the Outer Rim Territories. It contained the planet of Moltok, home to the Ho'Din and Makurth species."}, {"tag": "h2", "text": "Sources"}, {"tag": "h2", "text": "Notes and references"}]}