{"url": "Devaronese", "categories": ["Category:Canon articles", "Category:Language stubs", "Category:Languages"], "nodes": [{"tag": "h1", "text": "Devaronese"}, {"tag": "p", "text": "Devaronese was the language of the Devaronians, developing on the planet Devaron. The Devaronians were also capable of speaking Basic. Few Devaronians bothered to learn the language by the time of the Galactic Civil War, preferring to speak Basic in all situations."}, {"tag": "h2", "text": "Sources"}, {"tag": "h2", "text": "Notes and references"}]}