{"url": "Alex_Sanchez", "categories": ["Category:Real-world articles", "Category:Artist stubs", "Category:Comic book pencillers", "Category:Comic book inkers", "Category:Comic book colorists", "Category:Comic book letterers"], "nodes": [{"tag": "h1", "text": "Alex Sanchez"}, {"tag": "p", "text": "Alex Sanchez is an artist who is currently illustrating Star Wars: The Old Republic, Threat of Peace series of webcomics. He has previously done work on comics such as Marvel Age Hulk, X-Men, and various Dark Horse comics."}]}