{"url": "Ghhhk", "categories": ["Category:Canon articles", "Category:Creatures of Clak'dor VII", "Category:Creatures of unspecified biology", "Category:Creatures of unspecified diet", "Category:Dejarik", "Category:Species of undefined sentience"], "nodes": [{"tag": "h1", "text": "Ghhhk"}, {"tag": "p", "text": "The Ghhhk were an insectoid species hailing from the planet Bith whose appearance was used for one of the holographic pieces in the game dejarik. They were the apex predators of their homeward."}, {"tag": "h2", "text": "Appearances"}, {"tag": "h2", "text": "Sources"}, {"tag": "h2", "text": "Notes and references"}, {"tag": "h2", "text": "External links"}]}