{"url": "Ghia_Preyssola", "categories": ["Category:Legends articles", "Category:Alliance to Restore the Republic members", "Category:Females", "Category:Galactic Republic intelligence personnel", "Category:Nyriaan residents", "Category:Rutian Twi'leks"], "nodes": [{"tag": "h1", "text": "Ghia Preyssola"}, {"tag": "p", "text": "Ghia Preyssola was a female Twi'lek who served the Galactic Republic and later, the Alliance to Restore the Republic."}, {"tag": "h2", "text": "Biography"}, {"tag": "p", "text": "Preyssola worked for Republic Intelligence and was responsible for forming and co-ordinating Republic Intelligence cells in the Luire system. Following the invasion of the Luire system by the Confederacy of Independent Systems during the Clone Wars, Preyssola took refuge in the village Silence on Nyriaan, a planet in the Luire system. She re-emerged when the Republic regained control of Nyriaan, and later joined the Alliance to Restore the Republic."}, {"tag": "h2", "text": "Sources"}]}