{"url": "Gretalax", "categories": ["Category:Canon articles", "Category:Articles with spoilers", "Category:Creature stubs", "Category:Creatures of unspecified biology", "Category:Creatures of unspecified diet", "Category:Species of undefined sentience"], "nodes": [{"tag": "h1", "text": "Gretalax"}, {"tag": "p", "text": "The Gretalax was a creature found on Loreth. A Gretalax on Loreth terrorized local pioneers, who hired the former Jedi turned monster hunter Ty Yorrick with handling the creature."}, {"tag": "h2", "text": "Appearances"}, {"tag": "h2", "text": "Notes and references"}]}