{"url": "Groundlimo", "categories": ["Category:Legends articles", "Category:Vehicle stubs", "Category:Luxury vehicles", "Category:Hovercraft"], "nodes": [{"tag": "h1", "text": "Groundlimo"}, {"tag": "p", "text": "A groundlimo was a chauffeur-driven ground-effect vehicle that carried up to eight passengers. It was frequently employed by the affluent and influential classes. The groundlimo was the basic, unadorned version of the groundcoach."}, {"tag": "h2", "text": "Appearances"}, {"tag": "h2", "text": "Sources"}]}