{"url": "Halls_of_Knowledge/Legends", "categories": ["Category:Legends articles", "Category:Libraries", "Category:Locations of the Jedi Order", "Category:Twenty Wonders of the Galaxy"], "nodes": [{"tag": "h1", "text": "Halls of Knowledge"}, {"tag": "p", "text": "The Halls of Knowledge were storehouses of Jedi information on the planet Phateem."}, {"tag": "h2", "text": "History"}, {"tag": "p", "text": "It was once the largest repository of Force-imbued artifacts in the galaxy and included in the list of the Twenty Wonders of the Galaxy by Vicendi in 10,000 BBY. A vital location of the Jedi Order, most items found in its collection were later scattered to Jedi facilities on Ossus, Coruscant, Dantooine, Ilum, and Kamparas."}, {"tag": "h2", "text": "Appearances"}, {"tag": "h2", "text": "Sources"}, {"tag": "h2", "text": "Notes and references"}]}