{"url": "Jazbinan_bartender", "categories": ["Category:Legends articles", "Category:Articles with conjectural titles", "Category:Jazbinans", "Category:Males"], "nodes": [{"tag": "h1", "text": "Jazbinan bartender"}, {"tag": "p", "text": "This bartender was a Jazbinan who tended bar on Jazbina."}, {"tag": "h2", "text": "Biography"}, {"tag": "p", "text": "He was serving drinks at his bar and watched in shock when 3DVO transmitted a broadcast of an imprisoned Prepredenko, their monarch. He tried to maintain a business-as-usual attitude, continuing to serve drinks. He offered a new drink to a regular named Sebb. Sebb refused, believing the barkeep would laugh at his lack of desire to drink, even after what they had just witnessed. Contrary to Sebb's belief, the bartender refused to laugh."}, {"tag": "h2", "text": "Appearances"}]}