{"url": "Knave_Three", "categories": ["Category:Legends articles", "Category:Articles that are known by a nickname", "Category:New Republic Starfighter Corps personnel", "Category:Squadron callsigns", "Category:Unidentified humans", "Category:Unidentified males", "Category:Unidentified military personnel", "Category:Unidentified New Republic individuals"], "nodes": [{"tag": "h1", "text": "Knave Three"}, {"tag": "p", "text": "Knave Three was the callsign of a male Human pilot serving in the New Republic Starfighter Corps during the later stages of the Galactic Civil War."}, {"tag": "h2", "text": "Biography"}, {"tag": "p", "text": "A Human male joined the New Republic as a pilot and was assigned to Knave Squadron, a squadron of E-wings which was part of the New Republic Starfighter Corps. Going by the callsign Knave Three, the bearded Human flew his craft during the battle over Dac in 10 ABY. Attacking the enemy craft of the Galactic Empire, Knave Three's starfighter sustained damaged during the battle over the Calamari Sea. While the pilot attempted to eject from his doomed craft, he was killed when the starfighter crashed into the hull of the World Devastator Silencer-7."}, {"tag": "h2", "text": "Appearances"}, {"tag": "h2", "text": "Notes and references"}]}