{"url": "Krallys", "categories": ["Category:Legends articles", "Category:Creature stubs", "Category:Acklays", "Category:Named creatures"], "nodes": [{"tag": "h1", "text": "Krallys"}, {"tag": "p", "text": "Krallys the Wild was the name of an Acklay which escaped from the Coronet Zoo on Corellia in 3640 BBY and was subsequently killed."}, {"tag": "h2", "text": "Behind the scenes"}, {"tag": "p", "text": "Krallys appears in the video game Star Wars: The Old Republic as a Champion boss on Corellia. He is not directly involved in any quests, but can be killed for loot and as part of the achievement. This article assumes 100% game completion, which means he was killed."}, {"tag": "h2", "text": "Appearances"}]}