{"url": "Mart%C3%ADnez_Roca", "categories": ["Category:Real-world articles", "Category:Real world company stubs", "Category:Real-world publishing companies"], "nodes": [{"tag": "h1", "text": "Mart\u00ednez Roca"}, {"tag": "p", "text": "Ediciones Mart\u00ednez Roca, known commonly as Mart\u00ednez Roca, is a company formerly responsible for publishing many of the Spanish translations of Star Wars novels. The company prints both fiction and non-fiction. They focus primarily on historic novels, but also work with science fiction and fantasy. They acquired the rights to the Star Wars books in 1992, but sold them to Alberto Santos Editor in 2001."}, {"tag": "p", "text": "They have published twenty-nine adult novels and five young reader novels under the Star Wars name."}, {"tag": "h2", "text": "Star Wars bibliography"}, {"tag": "h3", "text": "Novels"}, {"tag": "h3", "text": "Novelizations"}, {"tag": "h3", "text": "Series"}, {"tag": "h3", "text": "Young readers"}, {"tag": "h2", "text": "External links"}]}