{"url": "Multi-tool", "categories": ["Category:Canon articles", "Category:Technology stubs", "Category:Tool kits"], "nodes": [{"tag": "h1", "text": "Multi-tool"}, {"tag": "p", "text": "A multi-tool was a device that could serve as nearly any tool a user needed by telescoping different prongs. It fitted in a utility belt and one of the uses was that of a hydrospanner. Temmin Wexley owned one during his time on Akiva."}, {"tag": "h2", "text": "Appearances"}, {"tag": "h2", "text": "Sources"}, {"tag": "h2", "text": "Notes and references"}]}