{"url": "Nyyv", "categories": ["Category:Legends articles", "Category:Business owners and executives", "Category:Males", "Category:Sullustans"], "nodes": [{"tag": "h1", "text": "Nyyv"}, {"tag": "p", "text": "Nyyv was a Sullustan native to the oceanic world of Vaynai. He owned and operated Uncle Nyyv's Floating Eatery, found on Streysel Island, during the height of the New Order. He was a native speaker of many languages, including Rodese."}, {"tag": "p", "text": "Translated into basic, the name \"Nyyv\" means \"flexible\"."}, {"tag": "h2", "text": "Sources"}, {"tag": "h2", "text": "Notes and references"}]}